{
  "version": 2,
  "desktopOnly": true,
  "items": [
    {
      "id": "pb-378f4f34-6cca-47a2-99d9-a240a248e31a",
      "title": "今日日记",
      "visible": true,
      "iconType": "iconpark",
      "iconValue": "iconpark:CalendarDot",
      "surface": "statusbar-right",
      "order": 0,
      "actionType": "builtin-global-command",
      "actionId": "dailyNote",
      "tooltip": ""
    },
    {
      "id": "pb-79368952-7aa4-4ee9-9caa-ecea414bad76",
      "title": "最近文档",
      "visible": true,
      "iconType": "iconpark",
      "iconValue": "iconpark:DocSearchTwo",
      "surface": "statusbar-right",
      "order": 1,
      "actionType": "experimental-shortcut",
      "actionId": "Ctrl+E",
      "tooltip": "",
      "experimentalShortcut": {
        "shortcut": "Ctrl+E",
        "sendEscapeBefore": false,
        "dispatchTarget": "auto",
        "allowDirectWindowDispatch": false
      }
    },
    {
      "id": "pb-76916412-1ea9-4cc4-b8cf-a3773a7ba003",
      "title": "数据历史",
      "visible": true,
      "iconType": "iconpark",
      "iconValue": "iconpark:History",
      "surface": "statusbar-right",
      "order": 2,
      "actionType": "experimental-shortcut",
      "actionId": "Alt+H",
      "tooltip": "",
      "experimentalShortcut": {
        "shortcut": "Alt+H",
        "sendEscapeBefore": false,
        "dispatchTarget": "auto",
        "allowDirectWindowDispatch": false
      }
    },
    {
      "id": "pb-88b89a52-3e8f-4f15-8cf9-99def14d42c7",
      "title": "集市",
      "visible": true,
      "iconType": "iconpark",
      "iconValue": "iconpark:WeixinMarket",
      "surface": "statusbar-right",
      "order": 3,
      "actionType": "experimental-click-sequence",
      "actionId": "barWorkspace",
      "tooltip": "",
      "experimentalClickSequence": {
        "steps": [
          {
            "selector": "barWorkspace",
            "valueMode": "value",
            "timeoutMs": 5000,
            "retryCount": 2,
            "retryDelayMs": 300,
            "delayAfterMs": 200
          },
          {
            "selector": "config",
            "valueMode": "value",
            "timeoutMs": 5000,
            "retryCount": 2,
            "retryDelayMs": 300,
            "delayAfterMs": 200
          },
          {
            "selector": "bazaar",
            "valueMode": "value",
            "timeoutMs": 5000,
            "retryCount": 2,
            "retryDelayMs": 300,
            "delayAfterMs": 200
          }
        ],
        "stopOnFailure": true
      }
    },
    {
      "id": "pb-ac74263a-43a7-438a-93fa-0e97a8a97859",
      "title": "重启所有插件",
      "visible": true,
      "iconType": "iconpark",
      "iconValue": "iconpark:FigmaResetInstance",
      "surface": "statusbar-right",
      "order": 4,
      "actionType": "builtin-global-command",
      "actionId": "restartPlugins",
      "tooltip": ""
    },
    {
      "id": "pb-72370934-8420-4c2b-abfa-928764ca6d84",
      "title": "切换到英文",
      "visible": true,
      "iconType": "iconpark",
      "iconValue": "iconpark:English",
      "surface": "statusbar-right",
      "order": 5,
      "actionType": "experimental-click-sequence",
      "actionId": "barWorkspace",
      "tooltip": "",
      "experimentalClickSequence": {
        "steps": [
          {
            "selector": "barWorkspace",
            "valueMode": "value",
            "timeoutMs": 5000,
            "retryCount": 1,
            "retryDelayMs": 300,
            "delayAfterMs": 200
          },
          {
            "selector": "config",
            "valueMode": "value",
            "timeoutMs": 5000,
            "retryCount": 1,
            "retryDelayMs": 300,
            "delayAfterMs": 200
          },
          {
            "selector": "appearance",
            "valueMode": "value",
            "timeoutMs": 5000,
            "retryCount": 1,
            "retryDelayMs": 300,
            "delayAfterMs": 200
          },
          {
            "selector": "lang",
            "value": "English (en_US)",
            "valueMode": "text",
            "timeoutMs": 5000,
            "retryCount": 1,
            "retryDelayMs": 300,
            "delayAfterMs": 200
          }
        ],
        "stopOnFailure": true
      }
    },
    {
      "id": "pb-d367924d-a9ac-4eae-91ec-69dcd19eaffd",
      "title": "切换到中文",
      "visible": true,
      "iconType": "iconpark",
      "iconValue": "iconpark:Chinese",
      "surface": "statusbar-right",
      "order": 6,
      "actionType": "experimental-click-sequence",
      "actionId": "barWorkspace",
      "tooltip": "",
      "experimentalClickSequence": {
        "steps": [
          {
            "selector": "barWorkspace",
            "valueMode": "value",
            "timeoutMs": 5000,
            "retryCount": 1,
            "retryDelayMs": 300,
            "delayAfterMs": 200
          },
          {
            "selector": "config",
            "valueMode": "value",
            "timeoutMs": 5000,
            "retryCount": 1,
            "retryDelayMs": 300,
            "delayAfterMs": 200
          },
          {
            "selector": "appearance",
            "valueMode": "value",
            "timeoutMs": 5000,
            "retryCount": 1,
            "retryDelayMs": 300,
            "delayAfterMs": 200
          },
          {
            "selector": "lang",
            "value": "简体中文 (zh_CN)",
            "valueMode": "text",
            "timeoutMs": 5000,
            "retryCount": 1,
            "retryDelayMs": 300,
            "delayAfterMs": 200
          }
        ],
        "stopOnFailure": true
      }
    },
    {
      "id": "pb-4f7c5741-8099-4f3a-b5b3-7921f1f74355",
      "title": "仅导出当前文档",
      "visible": true,
      "iconType": "iconpark",
      "iconValue": "iconpark:FileText",
      "surface": "canvas",
      "order": 7,
      "actionType": "plugin-command",
      "actionId": "siyuan-doc-assist:export-current",
      "tooltip": ""
    },
    {
      "id": "pb-4b654804-355d-4a3d-960f-8437e0f36e9b",
      "title": "随心按设置",
      "visible": true,
      "iconType": "iconpark",
      "iconValue": "iconpark:AsteriskKey",
      "surface": "statusbar-right",
      "order": 8,
      "actionType": "plugin-command",
      "actionId": "siyuan-power-buttons:open-settings",
      "tooltip": ""
    }
  ],
  "disabledNativeButtons": [],
  "experimental": {
    "nativeToolbarControl": false,
    "internalCommandAdapter": false,
    "shortcutAdapter": true,
    "clickSequenceAdapter": true
  }
}